membrain_stats/__init__.py
membrain_stats/mesh_conversion_cli.py
membrain_stats/appNapp/__init__.py
membrain_stats/appNapp/curvature.py
membrain_stats/appNapp/normal_tracing.py
membrain_stats/dataloading/__init__.py
membrain_stats/geodesic_distances/__init__.py
membrain_stats/geodesic_distances/geodesic_nearest_neighbors.py
membrain_stats/geodesic_distances/geodesic_nearest_neighbors_wrt.py
membrain_stats/geodesic_distances/geodesic_ripleys.py
membrain_stats/membrane_edges/__init__.py
membrain_stats/membrane_edges/edge_from_curvature.py
membrain_stats/membrane_edges/exclude_edge_positions.py
membrain_stats/protein_concentration/__init__.py
membrain_stats/protein_concentration/protein_concentration.py
membrain_stats/protein_concentration/protein_concentration_wrt.py
membrain_stats/utils/__init__.py
membrain_stats/utils/geodesic_distance_utils.py
membrain_stats/utils/io_utils.py
membrain_stats/utils/mesh_utils.py
membrain_stats/utils/pairwise_orientations_utils.py
membrain_stats/utils/ripley_utils.py
membrain_stats/utils/wrt_utils.py
membrain_stats-0.0.2.dist-info/METADATA
membrain_stats-0.0.2.dist-info/WHEEL
membrain_stats-0.0.2.dist-info/entry_points.txt
membrain_stats-0.0.2.dist-info/RECORD
